pybatch/__init__.py
pybatch/generic_protocol.py
pybatch/genericjob.py
pybatch/job_factory.py
pybatch/parameter.py
pybatch/tools.py
pybatch/plugins/local/__init__.py
pybatch/plugins/local/executor.py
pybatch/plugins/local/job.py
pybatch/plugins/local/plugin.py
pybatch/plugins/nobatch/__init__.py
pybatch/plugins/nobatch/job.py
pybatch/plugins/nobatch/plugin.py
pybatch/plugins/nobatch/pybatch_manager.py
pybatch/plugins/slurm/__init__.py
pybatch/plugins/slurm/job.py
pybatch/plugins/slurm/plugin.py
pybatch/protocols/__init__.py
pybatch/protocols/local.py
pybatch/protocols/paramiko.py
pybatch/protocols/ssh.py
salome_pybatch-1.0.dist-info/licenses/LICENSE
salome_pybatch-1.0.dist-info/METADATA
salome_pybatch-1.0.dist-info/WHEEL
salome_pybatch-1.0.dist-info/entry_points.txt
salome_pybatch-1.0.dist-info/top_level.txt
salome_pybatch-1.0.dist-info/RECORD
