Metadata-Version: 2.4
Name: salome-pybatch
Version: 1.0
Summary: Job management on remote computers.
Author-email: Ovidiu MIRCESCU <ovidiu.mircescu@edf.fr>
Classifier: Programming Language :: Python :: 3
Classifier: Operating System :: OS Independent
Requires-Python: >=3.9
License-File: LICENSE
Requires-Dist: psutil
Provides-Extra: paramiko
Requires-Dist: scp; extra == "paramiko"
Requires-Dist: paramiko[gssapi]; extra == "paramiko"
Provides-Extra: dev
Requires-Dist: tox>=4.0; extra == "dev"
Provides-Extra: docs
Requires-Dist: sphinx; extra == "docs"
Provides-Extra: lint
Requires-Dist: ruff; extra == "lint"
Provides-Extra: type
Requires-Dist: mypy; extra == "type"
Provides-Extra: test
Requires-Dist: pytest>=7; extra == "test"
Requires-Dist: pytest-xdist; extra == "test"
Requires-Dist: pytest-timeout; extra == "test"
Requires-Dist: pytest-html; extra == "test"
Requires-Dist: pytest-sugar; extra == "test"
Requires-Dist: tomli; python_version < "3.11" and extra == "test"
Provides-Extra: distrib
Requires-Dist: build; extra == "distrib"
Dynamic: license-file
